<?xml version="1.0" encoding="UTF-8"?>
<!DOCTYPE suite SYSTEM "https://testng.org/testng-1.0.dtd">
<suite name ="Suite">
	<test name = "Test">
		<parameter name = "username1" value = "Karuppannan"></parameter>
		<parameter name = "password1" value = "Amutha"></parameter>
		<parameter name = "firstName1" value = "Hemalatha"></parameter>
		<parameter name = "lastName1" value = "Karuppannan"></parameter>
		<parameter name = "day1" value = "15"></parameter>
		<parameter name = "month1" value = "8"></parameter>
		<parameter name = "year1" value = "1993"></parameter>
		<parameter name = "mobileNumber1" value = "6574839284"></parameter>
		<parameter name = "newPassword1" value = "HarshRithvik"></parameter>
		<classes>
			<class name = "org.dataPassToWebpageFromXmlFile.DataPassFromXmlFile"/>
			</classes>
		</test>
	</suite>